galaxy/__init__.py
galaxy/py.typed
galaxy/web/__init__.py
galaxy/web/form_builder.py
galaxy/web/statsd_client.py
galaxy/web/framework/__init__.py
galaxy/web/framework/base.py
galaxy/web/framework/decorators.py
galaxy/web/framework/helpers/__init__.py
galaxy/web/framework/helpers/grids.py
galaxy/web/framework/helpers/tags.py
galaxy/web/framework/middleware/__init__.py
galaxy/web/framework/middleware/error.py
galaxy/web/framework/middleware/profile.py
galaxy/web/framework/middleware/remoteuser.py
galaxy/web/framework/middleware/request_id.py
galaxy/web/framework/middleware/sqldebug.py
galaxy/web/framework/middleware/static.py
galaxy/web/framework/middleware/statsd.py
galaxy/web/framework/middleware/translogger.py
galaxy/web/framework/middleware/xforwardedhost.py
galaxy/web/legacy_framework/__init__.py
galaxy/web/legacy_framework/grids.py
galaxy/web/proxy/__init__.py
galaxy/web/proxy/js/Dockerfile
galaxy/web/proxy/js/README.md
galaxy/web/proxy/js/package.json
galaxy/web/proxy/js/lib/main.js
galaxy/web/proxy/js/lib/mapper.js
galaxy/web/proxy/js/lib/proxy.js
galaxy_web_framework-25.0.3.dist-info/licenses/LICENSE
galaxy_web_framework-25.0.3.dist-info/METADATA
galaxy_web_framework-25.0.3.dist-info/WHEEL
galaxy_web_framework-25.0.3.dist-info/top_level.txt
galaxy_web_framework-25.0.3.dist-info/RECORD
