Metadata-Version: 2.4
Name: galaxy-web-framework
Version: 25.0.3
Summary: Galaxy web framework
Home-page: https://github.com/galaxyproject/galaxy
Author: Galaxy Project and Community
Author-email: galaxy-committers@lists.galaxyproject.org
License: AFL
Keywords: Galaxy
Classifier: Development Status :: 5 - Production/Stable
Classifier: Environment :: Console
Classifier: Intended Audience :: Developers
Classifier: License :: OSI Approved :: Academic Free License (AFL)
Classifier: Natural Language :: English
Classifier: Operating System :: POSIX
Classifier: Programming Language :: Python :: 3
Classifier: Programming Language :: Python :: 3.9
Classifier: Programming Language :: Python :: 3.10
Classifier: Programming Language :: Python :: 3.11
Classifier: Programming Language :: Python :: 3.12
Classifier: Programming Language :: Python :: 3.13
Classifier: Topic :: Software Development
Classifier: Topic :: Software Development :: Code Generators
Classifier: Topic :: Software Development :: Testing
Requires-Python: >=3.9
License-File: LICENSE
Requires-Dist: galaxy-data
Requires-Dist: galaxy-util
Requires-Dist: babel
Requires-Dist: MarkupSafe
Requires-Dist: paste
Requires-Dist: pydantic>=2.7.4
Requires-Dist: requests
Requires-Dist: Routes
Requires-Dist: SQLAlchemy!=2.0.36,<2.1,>=2.0
Requires-Dist: WebOb
Dynamic: license-file
